py_qbull/__init__.py
py_qbull/errors.py
py_qbull/metrics.py
py_qbull/queue.py
py_qbull/types.py
py_qbull/worker.py
py_qbull-1.0.0.dist-info/licenses/LICENSE
py_qbull-1.0.0.dist-info/METADATA
py_qbull-1.0.0.dist-info/WHEEL
py_qbull-1.0.0.dist-info/top_level.txt
py_qbull-1.0.0.dist-info/RECORD
