Metadata-Version: 2.4
Name: py_qbull
Version: 1.0.0
Summary: A robust Python job queue library using Redis – Port of QBull
Author-email: FAZPI AI <dev@fazpi.ai>
License: MIT
Project-URL: Homepage, https://github.com/fazpi-ai/py-qbull
Project-URL: Documentation, https://github.com/fazpi-ai/py-qbull/tree/main/docs
Project-URL: Repository, https://github.com/fazpi-ai/py-qbull
Project-URL: Issues, https://github.com/fazpi-ai/py-qbull/issues
Keywords: queue,job,redis,worker,background,task,processing,async
Classifier: Development Status :: 5 - Production/Stable
Classifier: Intended Audience :: Developers
Classifier: License :: OSI Approved :: MIT License
Classifier: Programming Language :: Python :: 3
Classifier: Programming Language :: Python :: 3.8
Classifier: Programming Language :: Python :: 3.9
Classifier: Programming Language :: Python :: 3.10
Classifier: Programming Language :: Python :: 3.11
Classifier: Programming Language :: Python :: 3.12
Classifier: Topic :: Software Development :: Libraries :: Python Modules
Classifier: Topic :: System :: Distributed Computing
Requires-Python: >=3.8
License-File: LICENSE
Requires-Dist: redis>=5.0.0
Requires-Dist: asyncio-redis>=0.16.0
Requires-Dist: pydantic>=2.0.0
Requires-Dist: typing-extensions>=4.0.0
Dynamic: license-file
